mol2vec/__init__.py
mol2vec/features.py
mol2vec/helpers.py
mol2vec/app/__init__.py
mol2vec/app/mol2vec.py
mol2vec-0.2.2.dist-info/LICENSE
mol2vec-0.2.2.dist-info/METADATA
mol2vec-0.2.2.dist-info/WHEEL
mol2vec-0.2.2.dist-info/entry_points.txt
mol2vec-0.2.2.dist-info/top_level.txt
mol2vec-0.2.2.dist-info/RECORD
