Metadata-Version: 2.1
Name: mol2vec
Version: 0.2.2
Summary: Mol2vec - an unsupervised machine learning approach to learn vector representations of molecular                     substructures
Home-page: http://github.com/samoturk/mol2vec
Author: Samo Turk, Sabrina Jaeger, Simone Fulle
Author-email: samo.turk@gmail.com, sabrina.jaeger@t-online.de, fulle@bio.mx
License: BSD 3-clause
License-File: LICENSE
Requires-Dist: numpy
Requires-Dist: gensim
Requires-Dist: tqdm
Requires-Dist: joblib
Requires-Dist: pandas
Requires-Dist: matplotlib
Requires-Dist: IPython
Requires-Dist: seaborn
